pyracetrack/__init__.py
pyracetrack/approx_curve_func.py
pyracetrack/finite_line.py
pyracetrack/geom_utils.py
pyracetrack/interp_segment.py
pyracetrack/lines.py
pyracetrack/track.py
pyracetrack/track_element.py
pyracetrack/track_fast.py
pyracetrack/trajectory.py
pyracetrack/utils.py
pyracetrack/track_design/__init__.py
pyracetrack/track_design/designer.py
pyracetrack/track_design/designer_backup.py
pyracetrack-0.1.5.dist-info/LICENSE
pyracetrack-0.1.5.dist-info/METADATA
pyracetrack-0.1.5.dist-info/WHEEL
pyracetrack-0.1.5.dist-info/top_level.txt
pyracetrack-0.1.5.dist-info/RECORD
