Metadata-Version: 2.1
Name: pyracetrack
Version: 0.1.5
Summary: A python package for modelling 2D race tracks
Home-page: https://github.com/Hoeppke/pyracetrack
Author: Christoph Hoeppke
Author-email: hoeppke@maths.ox.ac.uk
License: UNKNOWN
Platform: UNKNOWN
Classifier: Programming Language :: Python :: 3
Classifier: License :: OSI Approved :: MIT License
Classifier: Operating System :: OS Independent
Requires-Python: >=3.7
License-File: LICENSE
Requires-Dist: numpy
Requires-Dist: matplotlib
Requires-Dist: tikzplot
Requires-Dist: numba
